pybso/__init__.py
pybso/charts.py
pybso/core.py
pybso/crossref_api.py
pybso/import_export.py
pybso/unpaywall_api.py
pybso/utils.py
pybso/data/sample.csv
pybso-1.1.0.dist-info/LICENSE
pybso-1.1.0.dist-info/METADATA
pybso-1.1.0.dist-info/WHEEL
pybso-1.1.0.dist-info/top_level.txt
pybso-1.1.0.dist-info/RECORD
