Metadata-Version: 2.1
Name: pybso
Version: 1.1.0
Summary: Open Access Monitoring from a DOI corpus
Home-page: https://github.com/gegedenice/pybso
Author: Géraldine Geoffroy
Author-email: geraldine.geoffroy@univ-cotedazur.fr
License: UNKNOWN
Platform: UNKNOWN
Classifier: Programming Language :: Python :: 3
Classifier: License :: OSI Approved :: MIT License
Classifier: Operating System :: OS Independent
Requires-Dist: pandas
Requires-Dist: requests
Requires-Dist: plotly
Requires-Dist: urllib3
